mkdocs_add_number_plugin/__init__.py
mkdocs_add_number_plugin/markdown.py
mkdocs_add_number_plugin/plugin.py
mkdocs_add_number_plugin/utils.py
mkdocs_add_number_plugin-1.2.2.dist-info/LICENSE
mkdocs_add_number_plugin-1.2.2.dist-info/METADATA
mkdocs_add_number_plugin-1.2.2.dist-info/WHEEL
mkdocs_add_number_plugin-1.2.2.dist-info/entry_points.txt
mkdocs_add_number_plugin-1.2.2.dist-info/top_level.txt
mkdocs_add_number_plugin-1.2.2.dist-info/RECORD
