Metadata-Version: 2.1
Name: mkdocs-add-number-plugin
Version: 1.2.2
Summary: MkDocs Plugin to automatically number the headings (h1-h6) in each markdown page and number the nav.
Home-page: https://github.com/shihr/mkdocs-add-number-plugin.git
Author: ignorantshr
Author-email: shrshraa@outlook.com
License: MIT
Keywords: mkdocs index add-number plugin
Platform: UNKNOWN
Classifier: Intended Audience :: Developers
Classifier: Intended Audience :: Information Technology
Classifier: License :: OSI Approved :: MIT License
Classifier: Programming Language :: Python
Classifier: Programming Language :: Python :: 3 :: Only
Classifier: Programming Language :: Python :: 3.5
Classifier: Programming Language :: Python :: 3.6
Classifier: Programming Language :: Python :: 3.7
Requires-Python: >=3.5
Requires-Dist: mkdocs (>=1.1)
